{
  "match_odds": {
    "Iraque|Noruega": {
      "p_home": 0.0717,
      "p_draw": 0.1444,
      "p_away": 0.7839,
      "n_bm": 23
    },
    "Argentina|Argélia": {
      "p_home": 0.6684,
      "p_draw": 0.214,
      "p_away": 0.1175,
      "n_bm": 24
    },
    "Áustria|Jordânia": {
      "p_home": 0.7074,
      "p_draw": 0.186,
      "p_away": 0.1066,
      "n_bm": 24
    },
    "Portugal|RD Congo": {
      "p_home": 0.7436,
      "p_draw": 0.1701,
      "p_away": 0.0863,
      "n_bm": 22
    },
    "Inglaterra|Croácia": {
      "p_home": 0.5543,
      "p_draw": 0.2558,
      "p_away": 0.1899,
      "n_bm": 24
    },
    "Gana|Panamá": {
      "p_home": 0.4299,
      "p_draw": 0.2902,
      "p_away": 0.28,
      "n_bm": 24
    },
    "Uzbequistão|Colômbia": {
      "p_home": 0.1005,
      "p_draw": 0.1998,
      "p_away": 0.6996,
      "n_bm": 24
    },
    "República Tcheca|África do Sul": {
      "p_home": 0.5409,
      "p_draw": 0.2553,
      "p_away": 0.2039,
      "n_bm": 24
    },
    "Suíça|Bosnia & Herzegovina": {
      "p_home": 0.6113,
      "p_draw": 0.2341,
      "p_away": 0.1546,
      "n_bm": 24
    },
    "Canadá|Catar": {
      "p_home": 0.747,
      "p_draw": 0.1694,
      "p_away": 0.0836,
      "n_bm": 24
    },
    "México|Coreia do Sul": {
      "p_home": 0.476,
      "p_draw": 0.2889,
      "p_away": 0.2352,
      "n_bm": 24
    },
    "Estados Unidos|Austrália": {
      "p_home": 0.5972,
      "p_draw": 0.2269,
      "p_away": 0.1759,
      "n_bm": 24
    },
    "Escócia|Marrocos": {
      "p_home": 0.1833,
      "p_draw": 0.2645,
      "p_away": 0.5522,
      "n_bm": 24
    },
    "Brasil|Haiti": {
      "p_home": 0.8697,
      "p_draw": 0.0879,
      "p_away": 0.0423,
      "n_bm": 24
    },
    "Turquia|Paraguai": {
      "p_home": 0.4722,
      "p_draw": 0.2845,
      "p_away": 0.2433,
      "n_bm": 24
    },
    "Holanda|Suécia": {
      "p_home": 0.5642,
      "p_draw": 0.2448,
      "p_away": 0.191,
      "n_bm": 23
    },
    "Alemanha|Costa do Marfim": {
      "p_home": 0.6222,
      "p_draw": 0.2151,
      "p_away": 0.1626,
      "n_bm": 24
    },
    "Equador|Curaçao": {
      "p_home": 0.8765,
      "p_draw": 0.0889,
      "p_away": 0.0346,
      "n_bm": 24
    },
    "Tunísia|Japão": {
      "p_home": 0.137,
      "p_draw": 0.2334,
      "p_away": 0.6296,
      "n_bm": 24
    },
    "Espanha|Arábia Saudita": {
      "p_home": 0.8682,
      "p_draw": 0.0947,
      "p_away": 0.0371,
      "n_bm": 24
    },
    "Bélgica|Irã": {
      "p_home": 0.6734,
      "p_draw": 0.2047,
      "p_away": 0.122,
      "n_bm": 22
    },
    "Uruguai|Cabo Verde": {
      "p_home": 0.6441,
      "p_draw": 0.2298,
      "p_away": 0.126,
      "n_bm": 22
    },
    "Nova Zelândia|Egito": {
      "p_home": 0.1733,
      "p_draw": 0.2385,
      "p_away": 0.5882,
      "n_bm": 22
    },
    "Argentina|Áustria": {
      "p_home": 0.5859,
      "p_draw": 0.2451,
      "p_away": 0.169,
      "n_bm": 21
    },
    "França|Iraque": {
      "p_home": 0.8615,
      "p_draw": 0.1014,
      "p_away": 0.0371,
      "n_bm": 21
    },
    "Noruega|Senegal": {
      "p_home": 0.4117,
      "p_draw": 0.277,
      "p_away": 0.3113,
      "n_bm": 20
    },
    "Jordânia|Argélia": {
      "p_home": 0.1397,
      "p_draw": 0.2238,
      "p_away": 0.6364,
      "n_bm": 21
    },
    "Portugal|Uzbequistão": {
      "p_home": 0.7721,
      "p_draw": 0.1497,
      "p_away": 0.0783,
      "n_bm": 22
    },
    "Inglaterra|Gana": {
      "p_home": 0.7253,
      "p_draw": 0.1763,
      "p_away": 0.0984,
      "n_bm": 22
    },
    "Panamá|Croácia": {
      "p_home": 0.1494,
      "p_draw": 0.2444,
      "p_away": 0.6062,
      "n_bm": 20
    },
    "Colômbia|RD Congo": {
      "p_home": 0.6457,
      "p_draw": 0.2255,
      "p_away": 0.1289,
      "n_bm": 20
    },
    "Bosnia & Herzegovina|Catar": {
      "p_home": 0.6085,
      "p_draw": 0.2372,
      "p_away": 0.1544,
      "n_bm": 18
    },
    "Suíça|Canadá": {
      "p_home": 0.4464,
      "p_draw": 0.2822,
      "p_away": 0.2714,
      "n_bm": 18
    },
    "Escócia|Brasil": {
      "p_home": 0.1406,
      "p_draw": 0.1975,
      "p_away": 0.6619,
      "n_bm": 18
    },
    "Marrocos|Haiti": {
      "p_home": 0.7335,
      "p_draw": 0.1725,
      "p_away": 0.094,
      "n_bm": 18
    },
    "República Tcheca|México": {
      "p_home": 0.2071,
      "p_draw": 0.2694,
      "p_away": 0.5234,
      "n_bm": 18
    },
    "África do Sul|Coreia do Sul": {
      "p_home": 0.1676,
      "p_draw": 0.2379,
      "p_away": 0.5945,
      "n_bm": 18
    },
    "Curaçao|Costa do Marfim": {
      "p_home": 0.0524,
      "p_draw": 0.1178,
      "p_away": 0.8297,
      "n_bm": 18
    },
    "Equador|Alemanha": {
      "p_home": 0.1972,
      "p_draw": 0.2516,
      "p_away": 0.5512,
      "n_bm": 18
    },
    "Japão|Suécia": {
      "p_home": 0.4484,
      "p_draw": 0.2768,
      "p_away": 0.2748,
      "n_bm": 18
    },
    "Tunísia|Holanda": {
      "p_home": 0.1031,
      "p_draw": 0.18,
      "p_away": 0.7168,
      "n_bm": 18
    },
    "Paraguai|Austrália": {
      "p_home": 0.4368,
      "p_draw": 0.2884,
      "p_away": 0.2748,
      "n_bm": 18
    },
    "Turquia|Estados Unidos": {
      "p_home": 0.339,
      "p_draw": 0.2646,
      "p_away": 0.3964,
      "n_bm": 18
    },
    "Noruega|França": {
      "p_home": 0.2223,
      "p_draw": 0.2598,
      "p_away": 0.5179,
      "n_bm": 18
    },
    "Senegal|Iraque": {
      "p_home": 0.6972,
      "p_draw": 0.1944,
      "p_away": 0.1084,
      "n_bm": 17
    },
    "Cabo Verde|Arábia Saudita": {
      "p_home": 0.3436,
      "p_draw": 0.2627,
      "p_away": 0.3936,
      "n_bm": 18
    },
    "Uruguai|Espanha": {
      "p_home": 0.1617,
      "p_draw": 0.2272,
      "p_away": 0.6111,
      "n_bm": 18
    },
    "Nova Zelândia|Bélgica": {
      "p_home": 0.0798,
      "p_draw": 0.1556,
      "p_away": 0.7645,
      "n_bm": 18
    },
    "Egito|Irã": {
      "p_home": 0.4487,
      "p_draw": 0.3047,
      "p_away": 0.2465,
      "n_bm": 18
    },
    "Croácia|Gana": {
      "p_home": 0.577,
      "p_draw": 0.2503,
      "p_away": 0.1727,
      "n_bm": 18
    },
    "Panamá|Inglaterra": {
      "p_home": 0.0961,
      "p_draw": 0.1578,
      "p_away": 0.7461,
      "n_bm": 17
    },
    "Colômbia|Portugal": {
      "p_home": 0.2703,
      "p_draw": 0.2854,
      "p_away": 0.4443,
      "n_bm": 17
    },
    "RD Congo|Uzbequistão": {
      "p_home": 0.4064,
      "p_draw": 0.2905,
      "p_away": 0.3031,
      "n_bm": 16
    },
    "Argélia|Áustria": {
      "p_home": 0.2644,
      "p_draw": 0.2981,
      "p_away": 0.4375,
      "n_bm": 16
    },
    "Jordânia|Argentina": {
      "p_home": 0.0694,
      "p_draw": 0.1387,
      "p_away": 0.7919,
      "n_bm": 16
    }
  },
  "champion_odds": {
    "França": 17.45,
    "Espanha": 13.03,
    "Inglaterra": 10.91,
    "Portugal": 9.92,
    "Argentina": 7.93,
    "Brasil": 6.98,
    "Alemanha": 6.02,
    "Holanda": 4.36,
    "Noruega": 2.69,
    "Marrocos": 2.3,
    "Estados Unidos": 1.96,
    "Bélgica": 1.92,
    "Japão": 1.73,
    "México": 1.33,
    "Colômbia": 1.44,
    "Suíça": 0.99,
    "Senegal": 0.83,
    "Uruguai": 0.84,
    "Croácia": 0.76,
    "Suécia": 0.76,
    "Austrália": 0.67,
    "Equador": 0.53,
    "Costa do Marfim": 0.5,
    "Turquia": 0.47,
    "Áustria": 0.5,
    "Coreia do Sul": 0.32,
    "Canadá": 0.35,
    "Egito": 0.29,
    "Escócia": 0.31,
    "Argélia": 0.18,
    "Gana": 0.15,
    "República Tcheca": 0.14,
    "Bosnia & Herzegovina": 0.15,
    "Paraguai": 0.13,
    "Tunísia": 0.12,
    "Irã": 0.12,
    "Jordânia": 0.06,
    "Uzbequistão": 0.07,
    "Nova Zelândia": 0.07,
    "Catar": 0.09,
    "Arábia Saudita": 0.12,
    "Cabo Verde": 0.09,
    "África do Sul": 0.07,
    "Curaçao": 0.06,
    "RD Congo": 0.1,
    "Haiti": 0.06,
    "Iraque": 0.09,
    "Panamá": 0.09
  }
}