{
  "champion": {
    "México": 4.51,
    "África do Sul": 0.12,
    "Coreia do Sul": 1.76,
    "República Tcheca": 1.09,
    "Canadá": 1.07,
    "Catar": 0.17,
    "Suíça": 1.97,
    "Bósnia e Herzegovina": 0.49,
    "Brasil": 6.96,
    "Marrocos": 2.58,
    "Haiti": 0.02,
    "Escócia": 0.97,
    "Estados Unidos": 1.1,
    "Paraguai": 0.26,
    "Austrália": 1.05,
    "Turquia": 0.54,
    "Alemanha": 3.08,
    "Curaçao": 0.06,
    "Costa do Marfim": 0.29,
    "Equador": 1.19,
    "Holanda": 7.45,
    "Japão": 1.33,
    "Tunísia": 0.7,
    "Suécia": 1.19,
    "Bélgica": 7.39,
    "Egito": 0.67,
    "Irã": 1.09,
    "Nova Zelândia": 0.1,
    "Espanha": 10.62,
    "Cabo Verde": 0.03,
    "Arábia Saudita": 0.05,
    "Uruguai": 0.91,
    "França": 10.35,
    "Senegal": 1.14,
    "Noruega": 4.24,
    "Iraque": 0.0,
    "Argentina": 5.9,
    "Argélia": 0.2,
    "Áustria": 0.94,
    "Jordânia": 0.01,
    "Portugal": 8.25,
    "Uzbequistão": 0.06,
    "Colômbia": 2.23,
    "RD Congo": 0.15,
    "Inglaterra": 2.97,
    "Croácia": 2.74,
    "Gana": 0.03,
    "Panamá": 0.03
  },
  "final": {
    "México": 9.53,
    "África do Sul": 0.33,
    "Coreia do Sul": 4.47,
    "República Tcheca": 2.47,
    "Canadá": 2.51,
    "Catar": 0.61,
    "Suíça": 4.38,
    "Bósnia e Herzegovina": 1.33,
    "Brasil": 14.3,
    "Marrocos": 5.98,
    "Haiti": 0.07,
    "Escócia": 2.39,
    "Estados Unidos": 3.09,
    "Paraguai": 0.71,
    "Austrália": 2.29,
    "Turquia": 1.44,
    "Alemanha": 7.02,
    "Curaçao": 0.16,
    "Costa do Marfim": 0.86,
    "Equador": 2.9,
    "Holanda": 12.73,
    "Japão": 3.04,
    "Tunísia": 1.6,
    "Suécia": 2.66,
    "Bélgica": 14.15,
    "Egito": 1.55,
    "Irã": 2.4,
    "Nova Zelândia": 0.28,
    "Espanha": 16.58,
    "Cabo Verde": 0.08,
    "Arábia Saudita": 0.19,
    "Uruguai": 2.03,
    "França": 17.95,
    "Senegal": 2.59,
    "Noruega": 9.29,
    "Iraque": 0.05,
    "Argentina": 10.45,
    "Argélia": 0.66,
    "Áustria": 2.33,
    "Jordânia": 0.06,
    "Portugal": 15.33,
    "Uzbequistão": 0.21,
    "Colômbia": 5.15,
    "RD Congo": 0.49,
    "Inglaterra": 5.77,
    "Croácia": 5.38,
    "Gana": 0.08,
    "Panamá": 0.1
  },
  "semi": {
    "México": 9.53,
    "África do Sul": 0.33,
    "Coreia do Sul": 4.47,
    "República Tcheca": 2.47,
    "Canadá": 2.51,
    "Catar": 0.61,
    "Suíça": 4.38,
    "Bósnia e Herzegovina": 1.33,
    "Brasil": 14.3,
    "Marrocos": 5.98,
    "Haiti": 0.07,
    "Escócia": 2.39,
    "Estados Unidos": 3.09,
    "Paraguai": 0.71,
    "Austrália": 2.29,
    "Turquia": 1.44,
    "Alemanha": 7.02,
    "Curaçao": 0.16,
    "Costa do Marfim": 0.86,
    "Equador": 2.9,
    "Holanda": 12.73,
    "Japão": 3.04,
    "Tunísia": 1.6,
    "Suécia": 2.66,
    "Bélgica": 14.15,
    "Egito": 1.55,
    "Irã": 2.4,
    "Nova Zelândia": 0.28,
    "Espanha": 16.58,
    "Cabo Verde": 0.08,
    "Arábia Saudita": 0.19,
    "Uruguai": 2.03,
    "França": 17.95,
    "Senegal": 2.59,
    "Noruega": 9.29,
    "Iraque": 0.05,
    "Argentina": 10.45,
    "Argélia": 0.66,
    "Áustria": 2.33,
    "Jordânia": 0.06,
    "Portugal": 15.33,
    "Uzbequistão": 0.21,
    "Colômbia": 5.15,
    "RD Congo": 0.49,
    "Inglaterra": 5.77,
    "Croácia": 5.38,
    "Gana": 0.08,
    "Panamá": 0.1
  },
  "quarter": {
    "México": 20.85,
    "África do Sul": 1.07,
    "Coreia do Sul": 11.39,
    "República Tcheca": 6.31,
    "Canadá": 5.97,
    "Catar": 1.9,
    "Suíça": 10.27,
    "Bósnia e Herzegovina": 3.7,
    "Brasil": 28.04,
    "Marrocos": 13.98,
    "Haiti": 0.23,
    "Escócia": 6.46,
    "Estados Unidos": 8.57,
    "Paraguai": 2.06,
    "Austrália": 5.04,
    "Turquia": 3.96,
    "Alemanha": 16.18,
    "Curaçao": 0.61,
    "Costa do Marfim": 2.94,
    "Equador": 6.95,
    "Holanda": 21.57,
    "Japão": 6.35,
    "Tunísia": 3.55,
    "Suécia": 5.73,
    "Bélgica": 24.09,
    "Egito": 4.71,
    "Irã": 5.55,
    "Nova Zelândia": 0.95,
    "Espanha": 25.45,
    "Cabo Verde": 0.4,
    "Arábia Saudita": 0.6,
    "Uruguai": 4.66,
    "França": 29.25,
    "Senegal": 6.15,
    "Noruega": 16.87,
    "Iraque": 0.27,
    "Argentina": 16.81,
    "Argélia": 1.7,
    "Áustria": 4.92,
    "Jordânia": 0.22,
    "Portugal": 26.92,
    "Uzbequistão": 0.72,
    "Colômbia": 11.22,
    "RD Congo": 1.42,
    "Inglaterra": 11.95,
    "Croácia": 10.71,
    "Gana": 0.4,
    "Panamá": 0.37
  },
  "round16": {
    "México": 39.43,
    "África do Sul": 2.91,
    "Coreia do Sul": 24.04,
    "República Tcheca": 14.47,
    "Canadá": 13.39,
    "Catar": 5.8,
    "Suíça": 20.27,
    "Bósnia e Herzegovina": 10.27,
    "Brasil": 47.85,
    "Marrocos": 27.47,
    "Haiti": 0.84,
    "Escócia": 15.0,
    "Estados Unidos": 16.68,
    "Paraguai": 5.03,
    "Austrália": 11.73,
    "Turquia": 9.22,
    "Alemanha": 33.65,
    "Curaçao": 1.76,
    "Costa do Marfim": 8.38,
    "Equador": 16.71,
    "Holanda": 37.79,
    "Japão": 14.18,
    "Tunísia": 7.99,
    "Suécia": 11.67,
    "Bélgica": 42.02,
    "Egito": 12.95,
    "Irã": 12.7,
    "Nova Zelândia": 3.3,
    "Espanha": 42.55,
    "Cabo Verde": 1.84,
    "Arábia Saudita": 2.48,
    "Uruguai": 13.16,
    "França": 51.14,
    "Senegal": 13.54,
    "Noruega": 29.06,
    "Iraque": 0.97,
    "Argentina": 29.47,
    "Argélia": 4.45,
    "Áustria": 10.53,
    "Jordânia": 0.82,
    "Portugal": 49.83,
    "Uzbequistão": 2.5,
    "Colômbia": 25.37,
    "RD Congo": 4.57,
    "Inglaterra": 25.01,
    "Croácia": 21.4,
    "Gana": 1.92,
    "Panamá": 1.88
  },
  "round32": {
    "México": 66.9,
    "África do Sul": 9.83,
    "Coreia do Sul": 50.02,
    "República Tcheca": 33.82,
    "Canadá": 29.19,
    "Catar": 15.83,
    "Suíça": 37.73,
    "Bósnia e Herzegovina": 24.23,
    "Brasil": 77.28,
    "Marrocos": 54.62,
    "Haiti": 3.87,
    "Escócia": 36.95,
    "Estados Unidos": 33.68,
    "Paraguai": 14.7,
    "Austrália": 26.21,
    "Turquia": 22.6,
    "Alemanha": 64.71,
    "Curaçao": 6.83,
    "Costa do Marfim": 25.12,
    "Equador": 38.48,
    "Holanda": 56.25,
    "Japão": 31.36,
    "Tunísia": 19.27,
    "Suécia": 26.96,
    "Bélgica": 72.84,
    "Egito": 32.16,
    "Irã": 30.51,
    "Nova Zelândia": 10.92,
    "Espanha": 63.1,
    "Cabo Verde": 8.12,
    "Arábia Saudita": 10.76,
    "Uruguai": 33.68,
    "França": 80.94,
    "Senegal": 33.48,
    "Noruega": 55.46,
    "Iraque": 4.23,
    "Argentina": 48.86,
    "Argélia": 14.54,
    "Áustria": 28.48,
    "Jordânia": 3.92,
    "Portugal": 81.12,
    "Uzbequistão": 9.24,
    "Colômbia": 53.44,
    "RD Congo": 14.51,
    "Inglaterra": 45.24,
    "Croácia": 42.69,
    "Gana": 8.01,
    "Panamá": 7.31
  },
  "group_adv": {
    "México": 92.0,
    "África do Sul": 35.78,
    "Coreia do Sul": 83.87,
    "República Tcheca": 70.12,
    "Canadá": 77.97,
    "Catar": 47.6,
    "Suíça": 86.2,
    "Bósnia e Herzegovina": 72.45,
    "Brasil": 93.88,
    "Marrocos": 86.54,
    "Haiti": 18.55,
    "Escócia": 78.75,
    "Estados Unidos": 88.53,
    "Paraguai": 53.04,
    "Austrália": 68.25,
    "Turquia": 68.8,
    "Alemanha": 94.95,
    "Curaçao": 25.83,
    "Costa do Marfim": 72.13,
    "Equador": 80.98,
    "Holanda": 89.27,
    "Japão": 71.94,
    "Tunísia": 48.04,
    "Suécia": 63.13,
    "Bélgica": 93.53,
    "Egito": 73.68,
    "Irã": 64.91,
    "Nova Zelândia": 34.57,
    "Espanha": 97.55,
    "Cabo Verde": 35.27,
    "Arábia Saudita": 39.81,
    "Uruguai": 82.83,
    "França": 93.29,
    "Senegal": 67.09,
    "Noruega": 82.7,
    "Iraque": 16.71,
    "Argentina": 92.82,
    "Argélia": 57.07,
    "Áustria": 80.22,
    "Jordânia": 25.52,
    "Portugal": 93.2,
    "Uzbequistão": 30.0,
    "Colômbia": 84.52,
    "RD Congo": 40.55,
    "Inglaterra": 90.75,
    "Croácia": 84.17,
    "Gana": 37.75,
    "Panamá": 32.88
  },
  "brasil_argentina": {
    "round32": 0.39,
    "round16": 0.18,
    "quarter": 0.14,
    "semi": 1.22,
    "final": 1.07,
    "any": 3.0
  },
  "n_sims": 100000,
  "blend_alpha": 0.65
}