{
  "champion": {
    "México": 3.32,
    "África do Sul": 0.0,
    "Coreia do Sul": 0.0,
    "República Tcheca": 0.0,
    "Canadá": 1.61,
    "Catar": 0.0,
    "Suíça": 3.07,
    "Bósnia e Herzegovina": 0.0,
    "Brasil": 9.45,
    "Marrocos": 3.9,
    "Haiti": 0.0,
    "Escócia": 0.0,
    "Estados Unidos": 1.3,
    "Paraguai": 0.75,
    "Austrália": 1.16,
    "Turquia": 0.0,
    "Alemanha": 0.0,
    "Curaçao": 0.0,
    "Costa do Marfim": 0.0,
    "Equador": 0.0,
    "Holanda": 0.0,
    "Japão": 0.0,
    "Tunísia": 0.0,
    "Suécia": 0.0,
    "Bélgica": 6.68,
    "Egito": 0.24,
    "Irã": 0.0,
    "Nova Zelândia": 0.0,
    "Espanha": 14.49,
    "Cabo Verde": 0.07,
    "Arábia Saudita": 0.0,
    "Uruguai": 0.0,
    "França": 16.84,
    "Senegal": 0.0,
    "Noruega": 2.96,
    "Iraque": 0.0,
    "Argentina": 17.07,
    "Argélia": 0.16,
    "Áustria": 0.0,
    "Jordânia": 0.0,
    "Portugal": 4.81,
    "Uzbequistão": 0.0,
    "Colômbia": 3.83,
    "RD Congo": 0.0,
    "Inglaterra": 7.14,
    "Croácia": 1.12,
    "Gana": 0.02,
    "Panamá": 0.0
  },
  "final": {
    "México": 8.16,
    "África do Sul": 0.0,
    "Coreia do Sul": 0.0,
    "República Tcheca": 0.0,
    "Canadá": 4.39,
    "Catar": 0.0,
    "Suíça": 7.35,
    "Bósnia e Herzegovina": 0.0,
    "Brasil": 18.11,
    "Marrocos": 9.54,
    "Haiti": 0.0,
    "Escócia": 0.0,
    "Estados Unidos": 3.5,
    "Paraguai": 2.48,
    "Austrália": 3.52,
    "Turquia": 0.0,
    "Alemanha": 0.0,
    "Curaçao": 0.0,
    "Costa do Marfim": 0.0,
    "Equador": 0.0,
    "Holanda": 0.0,
    "Japão": 0.0,
    "Tunísia": 0.0,
    "Suécia": 0.0,
    "Bélgica": 13.63,
    "Egito": 1.03,
    "Irã": 0.0,
    "Nova Zelândia": 0.0,
    "Espanha": 24.75,
    "Cabo Verde": 0.35,
    "Arábia Saudita": 0.0,
    "Uruguai": 0.0,
    "França": 30.05,
    "Senegal": 0.0,
    "Noruega": 7.43,
    "Iraque": 0.0,
    "Argentina": 29.44,
    "Argélia": 0.85,
    "Áustria": 0.0,
    "Jordânia": 0.0,
    "Portugal": 9.05,
    "Uzbequistão": 0.0,
    "Colômbia": 8.87,
    "RD Congo": 0.0,
    "Inglaterra": 14.73,
    "Croácia": 2.61,
    "Gana": 0.17,
    "Panamá": 0.0
  },
  "semi": {
    "México": 8.16,
    "África do Sul": 0.0,
    "Coreia do Sul": 0.0,
    "República Tcheca": 0.0,
    "Canadá": 4.39,
    "Catar": 0.0,
    "Suíça": 7.35,
    "Bósnia e Herzegovina": 0.0,
    "Brasil": 18.11,
    "Marrocos": 9.54,
    "Haiti": 0.0,
    "Escócia": 0.0,
    "Estados Unidos": 3.5,
    "Paraguai": 2.48,
    "Austrália": 3.52,
    "Turquia": 0.0,
    "Alemanha": 0.0,
    "Curaçao": 0.0,
    "Costa do Marfim": 0.0,
    "Equador": 0.0,
    "Holanda": 0.0,
    "Japão": 0.0,
    "Tunísia": 0.0,
    "Suécia": 0.0,
    "Bélgica": 13.63,
    "Egito": 1.03,
    "Irã": 0.0,
    "Nova Zelândia": 0.0,
    "Espanha": 24.75,
    "Cabo Verde": 0.35,
    "Arábia Saudita": 0.0,
    "Uruguai": 0.0,
    "França": 30.05,
    "Senegal": 0.0,
    "Noruega": 7.43,
    "Iraque": 0.0,
    "Argentina": 29.44,
    "Argélia": 0.85,
    "Áustria": 0.0,
    "Jordânia": 0.0,
    "Portugal": 9.05,
    "Uzbequistão": 0.0,
    "Colômbia": 8.87,
    "RD Congo": 0.0,
    "Inglaterra": 14.73,
    "Croácia": 2.61,
    "Gana": 0.17,
    "Panamá": 0.0
  },
  "quarter": {
    "México": 19.14,
    "África do Sul": 0.0,
    "Coreia do Sul": 0.0,
    "República Tcheca": 0.0,
    "Canadá": 12.2,
    "Catar": 0.0,
    "Suíça": 15.45,
    "Bósnia e Herzegovina": 0.0,
    "Brasil": 33.79,
    "Marrocos": 23.74,
    "Haiti": 0.0,
    "Escócia": 0.0,
    "Estados Unidos": 9.93,
    "Paraguai": 9.63,
    "Austrália": 9.74,
    "Turquia": 0.0,
    "Alemanha": 0.0,
    "Curaçao": 0.0,
    "Costa do Marfim": 0.0,
    "Equador": 0.0,
    "Holanda": 0.0,
    "Japão": 0.0,
    "Tunísia": 0.0,
    "Suécia": 0.0,
    "Bélgica": 27.11,
    "Egito": 3.53,
    "Irã": 0.0,
    "Nova Zelândia": 0.0,
    "Espanha": 40.98,
    "Cabo Verde": 1.71,
    "Arábia Saudita": 0.0,
    "Uruguai": 0.0,
    "França": 54.43,
    "Senegal": 0.0,
    "Noruega": 17.01,
    "Iraque": 0.0,
    "Argentina": 46.38,
    "Argélia": 3.37,
    "Áustria": 0.0,
    "Jordânia": 0.0,
    "Portugal": 16.1,
    "Uzbequistão": 0.0,
    "Colômbia": 18.87,
    "RD Congo": 0.0,
    "Inglaterra": 30.05,
    "Croácia": 5.87,
    "Gana": 0.94,
    "Panamá": 0.0
  },
  "round16": {
    "México": 45.17,
    "África do Sul": 0.0,
    "Coreia do Sul": 0.0,
    "República Tcheca": 0.0,
    "Canadá": 43.31,
    "Catar": 0.0,
    "Suíça": 36.41,
    "Bósnia e Herzegovina": 0.0,
    "Brasil": 63.59,
    "Marrocos": 56.69,
    "Haiti": 0.0,
    "Escócia": 0.0,
    "Estados Unidos": 37.11,
    "Paraguai": 23.33,
    "Austrália": 19.43,
    "Turquia": 0.0,
    "Alemanha": 0.0,
    "Curaçao": 0.0,
    "Costa do Marfim": 0.0,
    "Equador": 0.0,
    "Holanda": 0.0,
    "Japão": 0.0,
    "Tunísia": 0.0,
    "Suécia": 0.0,
    "Bélgica": 62.89,
    "Egito": 8.21,
    "Irã": 0.0,
    "Nova Zelândia": 0.0,
    "Espanha": 60.57,
    "Cabo Verde": 5.78,
    "Arábia Saudita": 0.0,
    "Uruguai": 0.0,
    "França": 76.67,
    "Senegal": 0.0,
    "Noruega": 36.41,
    "Iraque": 0.0,
    "Argentina": 66.58,
    "Argélia": 13.08,
    "Áustria": 0.0,
    "Jordânia": 0.0,
    "Portugal": 26.37,
    "Uzbequistão": 0.0,
    "Colômbia": 45.68,
    "RD Congo": 0.0,
    "Inglaterra": 54.83,
    "Croácia": 13.06,
    "Gana": 4.83,
    "Panamá": 0.0
  },
  "round32": {
    "México": 100.0,
    "África do Sul": 0.0,
    "Coreia do Sul": 0.0,
    "República Tcheca": 0.0,
    "Canadá": 100.0,
    "Catar": 0.0,
    "Suíça": 69.95,
    "Bósnia e Herzegovina": 0.0,
    "Brasil": 100.0,
    "Marrocos": 100.0,
    "Haiti": 0.0,
    "Escócia": 0.0,
    "Estados Unidos": 100.0,
    "Paraguai": 100.0,
    "Austrália": 63.34,
    "Turquia": 0.0,
    "Alemanha": 0.0,
    "Curaçao": 0.0,
    "Costa do Marfim": 0.0,
    "Equador": 0.0,
    "Holanda": 0.0,
    "Japão": 0.0,
    "Tunísia": 0.0,
    "Suécia": 0.0,
    "Bélgica": 100.0,
    "Egito": 36.66,
    "Irã": 0.0,
    "Nova Zelândia": 0.0,
    "Espanha": 100.0,
    "Cabo Verde": 15.64,
    "Arábia Saudita": 0.0,
    "Uruguai": 0.0,
    "França": 100.0,
    "Senegal": 0.0,
    "Noruega": 100.0,
    "Iraque": 0.0,
    "Argentina": 84.36,
    "Argélia": 30.05,
    "Áustria": 0.0,
    "Jordânia": 0.0,
    "Portugal": 61.41,
    "Uzbequistão": 0.0,
    "Colômbia": 82.52,
    "RD Congo": 0.0,
    "Inglaterra": 100.0,
    "Croácia": 38.59,
    "Gana": 17.48,
    "Panamá": 0.0
  },
  "group_adv": {
    "México": 100.0,
    "África do Sul": 100.0,
    "Coreia do Sul": 0.0,
    "República Tcheca": 0.0,
    "Canadá": 100.0,
    "Catar": 0.0,
    "Suíça": 100.0,
    "Bósnia e Herzegovina": 100.0,
    "Brasil": 100.0,
    "Marrocos": 100.0,
    "Haiti": 0.0,
    "Escócia": 0.0,
    "Estados Unidos": 100.0,
    "Paraguai": 100.0,
    "Austrália": 100.0,
    "Turquia": 0.0,
    "Alemanha": 100.0,
    "Curaçao": 0.0,
    "Costa do Marfim": 100.0,
    "Equador": 100.0,
    "Holanda": 100.0,
    "Japão": 100.0,
    "Tunísia": 0.0,
    "Suécia": 100.0,
    "Bélgica": 100.0,
    "Egito": 100.0,
    "Irã": 0.0,
    "Nova Zelândia": 0.0,
    "Espanha": 100.0,
    "Cabo Verde": 100.0,
    "Arábia Saudita": 0.0,
    "Uruguai": 0.0,
    "França": 100.0,
    "Senegal": 100.0,
    "Noruega": 100.0,
    "Iraque": 0.0,
    "Argentina": 100.0,
    "Argélia": 100.0,
    "Áustria": 100.0,
    "Jordânia": 0.0,
    "Portugal": 100.0,
    "Uzbequistão": 0.0,
    "Colômbia": 100.0,
    "RD Congo": 100.0,
    "Inglaterra": 100.0,
    "Croácia": 100.0,
    "Gana": 100.0,
    "Panamá": 0.0
  },
  "brasil_argentina": {
    "round32": 0.0,
    "round16": 0.0,
    "quarter": 0.0,
    "semi": 15.68,
    "final": 0.0,
    "any": 15.68
  },
  "n_sims": 100000,
  "blend_alpha": 0.65
}